edg4llm/__init__.py
edg4llm/core/__init__.py
edg4llm/core/dataGenerators.py
edg4llm/core/interface.py
edg4llm/core/pipeline.py
edg4llm/generators/__init__.py
edg4llm/generators/text_generators/__init__.py
edg4llm/generators/text_generators/answer_generator.py
edg4llm/generators/text_generators/base_generator.py
edg4llm/generators/text_generators/dialogue_generator.py
edg4llm/generators/text_generators/question_generator.py
edg4llm/models/__init__.py
edg4llm/models/baseModel.py
edg4llm/models/chatglm.py
edg4llm/models/chatgpt.py
edg4llm/models/deepseek.py
edg4llm/models/internlm.py
edg4llm/processor/__init__.py
edg4llm/processor/postprocess.py
edg4llm/processor/preprocess.py
edg4llm/utils/__init__.py
edg4llm/utils/config.py
edg4llm/utils/data_utils.py
edg4llm/utils/exceptions.py
edg4llm/utils/list_supported_models.py
edg4llm/utils/logger.py
edg4llm/utils/template.py
edg4llm-1.0.15.dist-info/LICENSE
edg4llm-1.0.15.dist-info/METADATA
edg4llm-1.0.15.dist-info/WHEEL
edg4llm-1.0.15.dist-info/entry_points.txt
edg4llm-1.0.15.dist-info/top_level.txt
edg4llm-1.0.15.dist-info/RECORD
